{
  "id": 238,
  "ats_platform": "greenhouse",
  "company_slug": "gradle",
  "company_name": "Gradle",
  "title": "Senior Cloud Infrastructure Engineer",
  "location": "Europe",
  "url": "https://gradle.com/careers/open-roles/7538180/?gh_jid=7538180",
  "posted_at": "2026-04-01T14:14:56-04:00",
  "first_seen_at": "2026-04-10T13:15:58.489074",
  "last_seen_at": "2026-04-10T13:15:58.489074",
  "fit_score": 62,
  "score_reasoning": "Your AWS infrastructure experience (ECS, Docker, Terraform basics) provides a solid foundation, but this role centers on Kubernetes and advanced infrastructure-as-code—areas where your experience is limited to basic Docker usage and entry-level Terraform. The Senior title aligns well with your 7 years of backend experience and current responsibilities, and the remote Europe-based setup matches your Berlin location perfectly. However, the platform engineering focus and Kubernetes-heavy requirements represent a significant shift from your core distributed systems and backend microservices strength. While you've built observability and infrastructure components, this role asks for deeper IaC and Kubernetes platform expertise that would require meaningful ramp-up. The growth potential is moderate—platform engineering is an adjacent adjacent track, not your stated senior backend target, and the role emphasizes foundational platforms rather than the high-scale distributed systems challenges you're seeking.",
  "score_breakdown": {
    "dimensions": {
      "tech_stack_match": 60,
      "seniority_match": 80,
      "remote_location_fit": 95,
      "growth_potential": 55
    },
    "key_matches": [
      "AWS infrastructure",
      "Docker",
      "Terraform",
      "Infrastructure automation",
      "Distributed team",
      "Observability mindset"
    ],
    "red_flags": [
      "Kubernetes is a core requirement; your experience is limited to Docker basics",
      "Advanced IaC (Terraform) is essential; your experience is basic/foundational",
      "Platform engineering is adjacent to backend roles; may not build toward your senior backend goal",
      "Limited evidence of designing Kubernetes-based platforms or managing application platforms at scale",
      "Focus is infrastructure-first, not distributed systems or backend architecture"
    ],
    "fit_category": "",
    "apply_priority": "medium"
  },
  "scored_at": "2026-04-10T13:57:33.192402",
  "status": "scored",
  "dismissal_reason": null,
  "match_tier": "broad_match",
  "salary": null,
  "salary_min": null,
  "salary_max": null,
  "salary_currency": null,
  "is_sparse": false,
  "company_quality_signals": [],
  "description": "&lt;h2&gt;&lt;strong&gt;Who We Are&lt;/strong&gt;&lt;/h2&gt;\n&lt;p&gt;AI is changing how software gets built. Code production is becoming a commodity. The focus is shifting from writing code to orchestrating, verifying, and governing change – and the toolchain is the new constraint.&lt;/p&gt;\n&lt;p&gt;Gradle is at the center of this shift. We build Develocity, a toolchain observability and intelligence platform used by some of the world&#39;s leading software organizations – Netflix, Airbnb, Spotify, SAP, major global banks, and hundreds more. Develocity helps software teams achieve delivery excellence through deep observability, build and test acceleration, and AI-powered intelligence across the entire toolchain – with current support for Gradle Build Tool, Apache Maven™, sbt, npm, and Python.&lt;/p&gt;\n&lt;p&gt;We are an AI-native company. AI is not a feature we&#39;re bolting on – it&#39;s central to how we work, how we think about our product, and where we&#39;re heading. We&#39;re investing deeply in making Develocity&#39;s unique data and decades of domain expertise accessible to both humans and AI agents, with trust, evidence, and explainability at the core of everything we build.&lt;/p&gt;\n&lt;p&gt;We have partnered with the Apache Software Foundation, the Commonhaus Foundation, the Micronaut Foundation, and other OSS projects such as Spring, Quarkus, Kotlin, JUnit, AndroidX, and many more to bring the values of Develocity also to the OSS Community.&lt;/p&gt;\n&lt;h2&gt;&lt;strong&gt;Our Values&lt;/strong&gt;&lt;/h2&gt;\n&lt;p&gt;&lt;strong&gt;Seek to Understand: &lt;/strong&gt;Everything starts with listening and understanding; we strive to understand diverse viewpoints, problems, and motivations. Before we take action, we ensure we truly grasp the challenges, perspectives, and goals.&amp;nbsp;&lt;/p&gt;\n&lt;p&gt;&lt;strong&gt;Know the Why&lt;/strong&gt;: We approach our work with a clear sense of purpose, ensuring every step is deliberate and focused. We take meaningful action with urgency, but never at the expense of thoughtful consideration.&amp;nbsp;&lt;/p&gt;\n&lt;p&gt;&lt;strong&gt;Innovate &amp;amp; Iterate&lt;/strong&gt;: We embrace challenges and are not afraid to try new things, even if they might fail. With a deep understanding and a clear purpose, we can develop creative, bold solutions to tackle challenges.&lt;/p&gt;\n&lt;p&gt;&lt;strong&gt;Own the Outcome: &lt;/strong&gt;We are empowered to take initiative, and we maintain transparency in our work and its outcomes. When we execute, we take responsibility for our decisions, measure the success of our innovations, and learn from the results.&lt;/p&gt;\n&lt;h2&gt;&lt;strong&gt;Who You Are&lt;/strong&gt;&lt;/h2&gt;\n&lt;p&gt;We are looking for a Senior Cloud Infrastructure engineer with a demonstrated ability to design and build highly reliable cloud-native infrastructure components as part of a collaborative team.&lt;/p&gt;\n&lt;p&gt;Our ideal candidates are passionate about infrastructure automation and have a success record with automated deployment at scale. They take pride in delivering foundational platforms that feature development teams and users can rely on. In addition, they can effectively communicate complex concepts to experts and non-experts, contribute and articulate strong opinions, and thrive as part of a distributed team.&amp;nbsp;&lt;/p&gt;\n&lt;h2&gt;&lt;strong&gt;Responsibilities&lt;/strong&gt;&lt;/h2&gt;\n&lt;ul&gt;\n&lt;li&gt;Delivering core infrastructure the Develocity engineering teams depend on&lt;/li&gt;\n&lt;li&gt;Maintaining and enhancing our Kubernetes-based application platform&lt;/li&gt;\n&lt;li&gt;Collaborating with the SRE team to provide reliable production operations&lt;/li&gt;\n&lt;li&gt;Collaborating with the DevProd team to provide robust continuous delivery practices&lt;/li&gt;\n&lt;li&gt;Collaborating with the Security team to deliver secure infrastructure&lt;/li&gt;\n&lt;/ul&gt;\n&lt;h2&gt;&lt;strong&gt;Minimum qualifications&lt;/strong&gt;&lt;/h2&gt;\n&lt;ul&gt;\n&lt;li&gt;5 years of cloud infrastructure experience&lt;/li&gt;\n&lt;li&gt;Experience with AWS, GCP, or Azure&lt;/li&gt;\n&lt;li&gt;Experience building infrastructure automation with Terraform&lt;/li&gt;\n&lt;li&gt;Experience with Docker and Kubernetes&lt;/li&gt;\n&lt;li&gt;Experience with Unix/Linux operating systems&lt;/li&gt;\n&lt;li&gt;Experience with infrastructure as code and automated application deployment&lt;/li&gt;\n&lt;li&gt;Working proficiency and communication skills in written and verbal English&lt;/li&gt;\n&lt;/ul&gt;\n&lt;h2&gt;&lt;strong&gt;Preferred qualifications&lt;/strong&gt;&lt;/h2&gt;\n&lt;ul&gt;\n&lt;li&gt;Experience designing and developing Kubernetes-based application platforms&lt;/li&gt;\n&lt;li&gt;Familiarity with GitOps practices and tooling for infrastructure automation&lt;/li&gt;\n&lt;li&gt;Knowledge of industry best practices with regard to infrastructure security&lt;/li&gt;\n&lt;li&gt;Systematic problem-solving approach, coupled with effective communication skills&lt;/li&gt;\n&lt;li&gt;Interest and ability to learn new software development skills and techniques&lt;/li&gt;\n&lt;/ul&gt;\n&lt;h2&gt;&lt;strong&gt;What we offer&lt;/strong&gt;&lt;/h2&gt;\n&lt;ul&gt;\n&lt;li&gt;Shaping and improving the infrastructure platform that powers the Develocity engineering teams and underpins Gradle’s managed Develocity offerings&lt;/li&gt;\n&lt;li&gt;Close customer interaction with engineers from leading tech organizations&lt;/li&gt;\n&lt;li&gt;An automation-focused, test-driven engineering culture&lt;/li&gt;\n&lt;li&gt;Close collaboration with experienced and dedicated peer engineers&lt;/li&gt;\n&lt;li&gt;Opportunities for growth in technical and leadership responsibilities&lt;/li&gt;\n&lt;li&gt;In-person meetings, such as our annual company offsite and team meetings&lt;/li&gt;\n&lt;li&gt;Work from home in a remote-first environment&amp;nbsp;&lt;/li&gt;\n&lt;li&gt;Competitive salaries and equity grants&lt;/li&gt;\n&lt;/ul&gt;\n&lt;h2&gt;&lt;strong&gt;L&lt;/strong&gt;&lt;strong&gt;ocation&lt;/strong&gt;&lt;/h2&gt;\n&lt;ul&gt;\n&lt;li&gt;Remote, Europe-friendly timezone, with working conditions allowing seamless collaboration with your colleagues through email, chat, and video streaming&lt;/li&gt;\n&lt;/ul&gt;\n&lt;p&gt;&lt;br&gt;&lt;br&gt;&lt;/p&gt;"
}